{
  "doneTowers": [
    {
      "id": 0,
      "score": 1801174.75
    },
    {
      "id": 0,
      "score": 3185941.8
    },
    {
      "id": 1,
      "score": 3001382.37
    },
    {
      "id": 2,
      "score": 2954872.81
    },
    {
      "id": 3,
      "score": 2872036.53
    },
    {
      "id": 4,
      "score": 2889931.54
    },
    {
      "id": 5,
      "score": 2884303.65
    },
    {
      "id": 6,
      "score": 2920994.39
    },
    {
      "id": 7,
      "score": 2971693.59
    },
    {
      "id": 8,
      "score": 2888851.92
    },
    {
      "id": 9,
      "score": 3292227.43
    },
    {
      "id": 10,
      "score": 2658668.04
    },
    {
      "id": 11,
      "score": 2894960.72
    },
    {
      "id": 12,
      "score": 3302345.61
    },
    {
      "id": 13,
      "score": 3022990.97
    },
    {
      "id": 14,
      "score": 2821063.78
    },
    {
      "id": 15,
      "score": 2926251.67
    },
    {
      "id": 16,
      "score": 2952105.51
    },
    {
      "id": 17,
      "score": 3001132.95
    },
    {
      "id": 18,
      "score": 2883692.08
    },
    {
      "id": 19,
      "score": 2884912.69
    },
    {
      "id": 20,
      "score": 2801808.98
    }
  ],
  "score": 1434747.67,
  "tower": {
    "score": 0.0,
    "words": [
      {
        "dir": 1,
        "pos": [
          2,
          22,
          99
        ],
        "text": "осаливание"
      },
      {
        "dir": 1,
        "pos": [
          28,
          6,
          89
        ],
        "text": "подтекание"
      },
      {
        "dir": 2,
        "pos": [
          11,
          28,
          81
        ],
        "text": "вариоскопия"
      },
      {
        "dir": 1,
        "pos": [
          28,
          21,
          8
        ],
        "text": "пантограф"
      },
      {
        "dir": 2,
        "pos": [
          15,
          1,
          99
        ],
        "text": "деспотизм"
      },
      {
        "dir": 1,
        "pos": [
          25,
          22,
          99
        ],
        "text": "фальцгобель"
      },
      {
        "dir": 1,
        "pos": [
          13,
          9,
          99
        ],
        "text": "ходулочник"
      },
      {
        "dir": 1,
        "pos": [
          20,
          20,
          92
        ],
        "text": "спрашивание"
      },
      {
        "dir": 1,
        "pos": [
          9,
          28,
          81
        ],
        "text": "смехотворность"
      },
      {
        "dir": 1,
        "pos": [
          8,
          9,
          99
        ],
        "text": "квохтание"
      },
      {
        "dir": 1,
        "pos": [
          11,
          19,
          99
        ],
        "text": "киприотка"
      },
      {
        "dir": 1,
        "pos": [
          0,
          4,
          87
        ],
        "text": "патентоспособность"
      },
      {
        "dir": 1,
        "pos": [
          22,
          5,
          98
        ],
        "text": "искручивание"
      },
      {
        "dir": 1,
        "pos": [
          22,
          14,
          99
        ],
        "text": "океанограф"
      },
      {
        "dir": 3,
        "pos": [
          27,
          11,
          77
        ],
        "text": "человеколюбие"
      },
      {
        "dir": 1,
        "pos": [
          23,
          17,
          32
        ],
        "text": "телеграфирование"
      },
      {
        "dir": 3,
        "pos": [
          0,
          16,
          81
        ],
        "text": "неразложимость"
      },
      {
        "dir": 1,
        "pos": [
          5,
          25,
          87
        ],
        "text": "приговорённый"
      },
      {
        "dir": 3,
        "pos": [
          27,
          18,
          85
        ],
        "text": "гимнастёрка"
      },
      {
        "dir": 1,
        "pos": [
          13,
          14,
          99
        ],
        "text": "копировщица"
      },
      {
        "dir": 1,
        "pos": [
          20,
          11,
          97
        ],
        "text": "залегание"
      },
      {
        "dir": 2,
        "pos": [
          12,
          16,
          90
        ],
        "text": "прокажённая"
      },
      {
        "dir": 1,
        "pos": [
          29,
          11,
          80
        ],
        "text": "землевладение"
      },
      {
        "dir": 3,
        "pos": [
          26,
          8,
          89
        ],
        "text": "благочестие"
      },
      {
        "dir": 1,
        "pos": [
          28,
          9,
          93
        ],
        "text": "дожаривание"
      },
      {
        "dir": 3,
        "pos": [
          16,
          17,
          76
        ],
        "text": "подгрунтовка"
      },
      {
        "dir": 3,
        "pos": [
          11,
          10,
          95
        ],
        "text": "истребление"
      },
      {
        "dir": 1,
        "pos": [
          11,
          27,
          97
        ],
        "text": "навеивание"
      },
      {
        "dir": 1,
        "pos": [
          28,
          1,
          97
        ],
        "text": "неистребимость"
      },
      {
        "dir": 2,
        "pos": [
          0,
          0,
          12
        ],
        "text": "радиолюбитель"
      },
      {
        "dir": 1,
        "pos": [
          5,
          18,
          83
        ],
        "text": "водоподъёмник"
      },
      {
        "dir": 2,
        "pos": [
          6,
          0,
          87
        ],
        "text": "смачиватель"
      },
      {
        "dir": 3,
        "pos": [
          0,
          18,
          97
        ],
        "text": "латифундизм"
      },
      {
        "dir": 1,
        "pos": [
          26,
          14,
          96
        ],
        "text": "подновление"
      },
      {
        "dir": 3,
        "pos": [
          12,
          0,
          86
        ],
        "text": "нерадушность"
      },
      {
        "dir": 2,
        "pos": [
          21,
          21,
          18
        ],
        "text": "коптитель"
      },
      {
        "dir": 2,
        "pos": [
          7,
          21,
          99
        ],
        "text": "диссоциация"
      },
      {
        "dir": 1,
        "pos": [
          18,
          22,
          90
        ],
        "text": "многоликость"
      },
      {
        "dir": 1,
        "pos": [
          2,
          15,
          99
        ],
        "text": "унитаризм"
      },
      {
        "dir": 1,
        "pos": [
          23,
          24,
          99
        ],
        "text": "извержение"
      },
      {
        "dir": 1,
        "pos": [
          6,
          13,
          99
        ],
        "text": "конармия"
      },
      {
        "dir": 1,
        "pos": [
          11,
          14,
          99
        ],
        "text": "врачеватель"
      },
      {
        "dir": 2,
        "pos": [
          18,
          5,
          85
        ],
        "text": "считывание"
      },
      {
        "dir": 2,
        "pos": [
          8,
          9,
          87
        ],
        "text": "закругление"
      },
      {
        "dir": 2,
        "pos": [
          19,
          21,
          5
        ],
        "text": "проворность"
      },
      {
        "dir": 1,
        "pos": [
          13,
          11,
          99
        ],
        "text": "загонщик"
      },
      {
        "dir": 3,
        "pos": [
          18,
          11,
          81
        ],
        "text": "кронпринцесса"
      },
      {
        "dir": 1,
        "pos": [
          27,
          26,
          99
        ],
        "text": "прогностика"
      },
      {
        "dir": 1,
        "pos": [
          18,
          3,
          98
        ],
        "text": "хромосома"
      },
      {
        "dir": 1,
        "pos": [
          20,
          28,
          90
        ],
        "text": "уплачивание"
      },
      {
        "dir": 3,
        "pos": [
          0,
          2,
          64
        ],
        "text": "двуутробка"
      },
      {
        "dir": 1,
        "pos": [
          9,
          19,
          99
        ],
        "text": "обсечение"
      },
      {
        "dir": 1,
        "pos": [
          29,
          27,
          62
        ],
        "text": "человеколюбец"
      },
      {
        "dir": 2,
        "pos": [
          16,
          1,
          89
        ],
        "text": "канатопрядение"
      },
      {
        "dir": 3,
        "pos": [
          13,
          14,
          97
        ],
        "text": "предыдущее"
      },
      {
        "dir": 2,
        "pos": [
          9,
          12,
          89
        ],
        "text": "светобоязнь"
      },
      {
        "dir": 3,
        "pos": [
          2,
          10,
          97
        ],
        "text": "дрессировщица"
      },
      {
        "dir": 1,
        "pos": [
          12,
          2,
          95
        ],
        "text": "каравансарай"
      },
      {
        "dir": 1,
        "pos": [
          17,
          4,
          99
        ],
        "text": "прогуливающаяся"
      },
      {
        "dir": 3,
        "pos": [
          22,
          9,
          99
        ],
        "text": "глиптодонт"
      },
      {
        "dir": 2,
        "pos": [
          16,
          16,
          83
        ],
        "text": "пододеяльник"
      },
      {
        "dir": 1,
        "pos": [
          19,
          26,
          99
        ],
        "text": "силуэтист"
      },
      {
        "dir": 3,
        "pos": [
          21,
          8,
          85
        ],
        "text": "краскотёрка"
      },
      {
        "dir": 2,
        "pos": [
          0,
          11,
          87
        ],
        "text": "брюзгливость"
      },
      {
        "dir": 2,
        "pos": [
          3,
          27,
          85
        ],
        "text": "прасольщица"
      },
      {
        "dir": 2,
        "pos": [
          8,
          26,
          99
        ],
        "text": "несмолкаемость"
      },
      {
        "dir": 1,
        "pos": [
          24,
          16,
          99
        ],
        "text": "авиалайнер"
      },
      {
        "dir": 2,
        "pos": [
          15,
          18,
          83
        ],
        "text": "выквашивание"
      },
      {
        "dir": 3,
        "pos": [
          10,
          6,
          81
        ],
        "text": "обобществление"
      },
      {
        "dir": 1,
        "pos": [
          6,
          17,
          96
        ],
        "text": "просевание"
      },
      {
        "dir": 1,
        "pos": [
          0,
          11,
          97
        ],
        "text": "отзвучие"
      },
      {
        "dir": 1,
        "pos": [
          10,
          4,
          93
        ],
        "text": "психология"
      },
      {
        "dir": 1,
        "pos": [
          24,
          10,
          89
        ],
        "text": "сопереживание"
      },
      {
        "dir": 3,
        "pos": [
          29,
          15,
          87
        ],
        "text": "разнашивание"
      },
      {
        "dir": 1,
        "pos": [
          26,
          1,
          99
        ],
        "text": "предупреждение"
      },
      {
        "dir": 1,
        "pos": [
          6,
          9,
          93
        ],
        "text": "брудергауз"
      },
      {
        "dir": 3,
        "pos": [
          28,
          18,
          8
        ],
        "text": "прапрабабка"
      },
      {
        "dir": 1,
        "pos": [
          22,
          7,
          95
        ],
        "text": "растратчица"
      },
      {
        "dir": 2,
        "pos": [
          0,
          4,
          68
        ],
        "text": "порождение"
      },
      {
        "dir": 3,
        "pos": [
          0,
          0,
          0
        ],
        "text": "культуристка"
      },
      {
        "dir": 1,
        "pos": [
          8,
          11,
          99
        ],
        "text": "дремотность"
      },
      {
        "dir": 2,
        "pos": [
          9,
          9,
          85
        ],
        "text": "протоплазма"
      },
      {
        "dir": 1,
        "pos": [
          4,
          9,
          99
        ],
        "text": "магнетизм"
      },
      {
        "dir": 1,
        "pos": [
          2,
          26,
          90
        ],
        "text": "кровожадность"
      },
      {
        "dir": 3,
        "pos": [
          5,
          19,
          99
        ],
        "text": "знатность"
      },
      {
        "dir": 1,
        "pos": [
          28,
          22,
          99
        ],
        "text": "цинкование"
      },
      {
        "dir": 1,
        "pos": [
          8,
          22,
          94
        ],
        "text": "расстраивание"
      },
      {
        "dir": 3,
        "pos": [
          25,
          19,
          93
        ],
        "text": "пиротехника"
      },
      {
        "dir": 2,
        "pos": [
          0,
          22,
          90
        ],
        "text": "уместность"
      },
      {
        "dir": 2,
        "pos": [
          11,
          12,
          84
        ],
        "text": "поработитель"
      },
      {
        "dir": 1,
        "pos": [
          24,
          1,
          98
        ],
        "text": "хиромантия"
      },
      {
        "dir": 2,
        "pos": [
          16,
          12,
          87
        ],
        "text": "зашифровывание"
      },
      {
        "dir": 3,
        "pos": [
          16,
          6,
          97
        ],
        "text": "масонство"
      },
      {
        "dir": 1,
        "pos": [
          12,
          24,
          94
        ],
        "text": "полиморфизм"
      },
      {
        "dir": 2,
        "pos": [
          11,
          21,
          8
        ],
        "text": "народовластие"
      },
      {
        "dir": 1,
        "pos": [
          7,
          28,
          84
        ],
        "text": "перепутывание"
      },
      {
        "dir": 3,
        "pos": [
          21,
          6,
          80
        ],
        "text": "провинциализм"
      },
      {
        "dir": 1,
        "pos": [
          27,
          21,
          92
        ],
        "text": "медоносность"
      },
      {
        "dir": 1,
        "pos": [
          29,
          28,
          99
        ],
        "text": "конституционность"
      },
      {
        "dir": 1,
        "pos": [
          21,
          10,
          86
        ],
        "text": "парнолистник"
      },
      {
        "dir": 2,
        "pos": [
          3,
          13,
          98
        ],
        "text": "недоверие"
      },
      {
        "dir": 1,
        "pos": [
          10,
          15,
          94
        ],
        "text": "поджигатель"
      },
      {
        "dir": 1,
        "pos": [
          10,
          6,
          87
        ],
        "text": "неравноправие"
      },
      {
        "dir": 2,
        "pos": [
          4,
          6,
          77
        ],
        "text": "замуровывание"
      },
      {
        "dir": 3,
        "pos": [
          2,
          5,
          87
        ],
        "text": "заведующий"
      },
      {
        "dir": 2,
        "pos": [
          19,
          22,
          96
        ],
        "text": "гуртильщик"
      },
      {
        "dir": 1,
        "pos": [
          8,
          0,
          95
        ],
        "text": "приобретатель"
      },
      {
        "dir": 2,
        "pos": [
          19,
          5,
          98
        ],
        "text": "лиричность"
      },
      {
        "dir": 1,
        "pos": [
          5,
          23,
          99
        ],
        "text": "несчастье"
      },
      {
        "dir": 3,
        "pos": [
          9,
          14,
          97
        ],
        "text": "дежурство"
      },
      {
        "dir": 1,
        "pos": [
          15,
          23,
          99
        ],
        "text": "шплинтовка"
      },
      {
        "dir": 3,
        "pos": [
          29,
          0,
          57
        ],
        "text": "определённость"
      },
      {
        "dir": 2,
        "pos": [
          9,
          7,
          99
        ],
        "text": "квартиргер"
      },
      {
        "dir": 3,
        "pos": [
          8,
          7,
          94
        ],
        "text": "авантюристка"
      },
      {
        "dir": 2,
        "pos": [
          20,
          21,
          2
        ],
        "text": "сильванер"
      },
      {
        "dir": 1,
        "pos": [
          25,
          18,
          88
        ],
        "text": "каноничность"
      },
      {
        "dir": 1,
        "pos": [
          19,
          0,
          55
        ],
        "text": "пересасывание"
      },
      {
        "dir": 1,
        "pos": [
          24,
          13,
          99
        ],
        "text": "булочник"
      },
      {
        "dir": 2,
        "pos": [
          18,
          24,
          98
        ],
        "text": "напалзывание"
      },
      {
        "dir": 1,
        "pos": [
          15,
          22,
          89
        ],
        "text": "выказывание"
      },
      {
        "dir": 3,
        "pos": [
          6,
          4,
          89
        ],
        "text": "льночесалка"
      },
      {
        "dir": 1,
        "pos": [
          15,
          15,
          99
        ],
        "text": "стёртость"
      },
      {
        "dir": 2,
        "pos": [
          1,
          29,
          95
        ],
        "text": "националистка"
      },
      {
        "dir": 3,
        "pos": [
          22,
          2,
          87
        ],
        "text": "материнство"
      },
      {
        "dir": 2,
        "pos": [
          18,
          0,
          54
        ],
        "text": "человечность"
      },
      {
        "dir": 1,
        "pos": [
          6,
          29,
          95
        ],
        "text": "нарукавник"
      },
      {
        "dir": 1,
        "pos": [
          7,
          23,
          99
        ],
        "text": "потасовка"
      },
      {
        "dir": 3,
        "pos": [
          2,
          19,
          84
        ],
        "text": "повязывание"
      },
      {
        "dir": 3,
        "pos": [
          24,
          0,
          91
        ],
        "text": "степенность"
      },
      {
        "dir": 2,
        "pos": [
          0,
          4,
          72
        ],
        "text": "сосредоточение"
      },
      {
        "dir": 1,
        "pos": [
          20,
          3,
          92
        ],
        "text": "обоготворение"
      },
      {
        "dir": 1,
        "pos": [
          0,
          22,
          88
        ],
        "text": "безусадочность"
      },
      {
        "dir": 3,
        "pos": [
          17,
          15,
          94
        ],
        "text": "монотипистка"
      },
      {
        "dir": 1,
        "pos": [
          2,
          8,
          94
        ],
        "text": "перемощение"
      },
      {
        "dir": 3,
        "pos": [
          10,
          0,
          96
        ],
        "text": "шаманство"
      },
      {
        "dir": 1,
        "pos": [
          6,
          11,
          99
        ],
        "text": "спорангий"
      },
      {
        "dir": 1,
        "pos": [
          0,
          26,
          90
        ],
        "text": "малоопытность"
      },
      {
        "dir": 2,
        "pos": [
          19,
          24,
          95
        ],
        "text": "батарейка"
      },
      {
        "dir": 1,
        "pos": [
          25,
          26,
          99
        ],
        "text": "преуменьшение"
      },
      {
        "dir": 3,
        "pos": [
          0,
          3,
          97
        ],
        "text": "германофоб"
      },
      {
        "dir": 1,
        "pos": [
          0,
          4,
          68
        ],
        "text": "послушница"
      },
      {
        "dir": 2,
        "pos": [
          20,
          7,
          97
        ],
        "text": "притязание"
      },
      {
        "dir": 1,
        "pos": [
          28,
          3,
          98
        ],
        "text": "медитация"
      },
      {
        "dir": 1,
        "pos": [
          17,
          16,
          98
        ],
        "text": "полуокружность"
      },
      {
        "dir": 2,
        "pos": [
          20,
          22,
          91
        ],
        "text": "собеседник"
      },
      {
        "dir": 1,
        "pos": [
          27,
          24,
          98
        ],
        "text": "ненатуральность"
      },
      {
        "dir": 1,
        "pos": [
          20,
          5,
          94
        ],
        "text": "продвижение"
      },
      {
        "dir": 2,
        "pos": [
          5,
          17,
          87
        ],
        "text": "дерзновение"
      },
      {
        "dir": 3,
        "pos": [
          28,
          3,
          95
        ],
        "text": "инквизиторство"
      },
      {
        "dir": 3,
        "pos": [
          2,
          2,
          99
        ],
        "text": "полярископ"
      },
      {
        "dir": 2,
        "pos": [
          0,
          25,
          96
        ],
        "text": "скоростница"
      },
      {
        "dir": 2,
        "pos": [
          12,
          9,
          94
        ],
        "text": "тонкопряха"
      },
      {
        "dir": 1,
        "pos": [
          0,
          11,
          16
        ],
        "text": "электроёмкость"
      },
      {
        "dir": 2,
        "pos": [
          16,
          28,
          99
        ],
        "text": "старшеклассник"
      },
      {
        "dir": 3,
        "pos": [
          24,
          6,
          99
        ],
        "text": "чернорабочая"
      },
      {
        "dir": 1,
        "pos": [
          29,
          21,
          34
        ],
        "text": "прирабатываемость"
      },
      {
        "dir": 1,
        "pos": [
          0,
          6,
          85
        ],
        "text": "кумысолечебница"
      },
      {
        "dir": 1,
        "pos": [
          20,
          7,
          99
        ],
        "text": "сапропелит"
      },
      {
        "dir": 2,
        "pos": [
          3,
          15,
          87
        ],
        "text": "соломистость"
      },
      {
        "dir": 1,
        "pos": [
          26,
          7,
          98
        ],
        "text": "факториал"
      },
      {
        "dir": 1,
        "pos": [
          7,
          4,
          68
        ],
        "text": "немногосложность"
      },
      {
        "dir": 3,
        "pos": [
          4,
          9,
          96
        ],
        "text": "нахлебничество"
      },
      {
        "dir": 3,
        "pos": [
          14,
          0,
          90
        ],
        "text": "гаулейтер"
      },
      {
        "dir": 2,
        "pos": [
          13,
          12,
          81
        ],
        "text": "проигрыватель"
      },
      {
        "dir": 2,
        "pos": [
          5,
          25,
          98
        ],
        "text": "венеролог"
      },
      {
        "dir": 2,
        "pos": [
          8,
          9,
          98
        ],
        "text": "высокопарность"
      },
      {
        "dir": 1,
        "pos": [
          20,
          13,
          99
        ],
        "text": "многоводье"
      },
      {
        "dir": 1,
        "pos": [
          2,
          2,
          97
        ],
        "text": "недовыручка"
      },
      {
        "dir": 2,
        "pos": [
          3,
          27,
          97
        ],
        "text": "соскребание"
      },
      {
        "dir": 1,
        "pos": [
          22,
          10,
          99
        ],
        "text": "лавирование"
      },
      {
        "dir": 1,
        "pos": [
          16,
          9,
          99
        ],
        "text": "прочность"
      },
      {
        "dir": 1,
        "pos": [
          21,
          29,
          98
        ],
        "text": "привыкание"
      },
      {
        "dir": 3,
        "pos": [
          0,
          1,
          37
        ],
        "text": "пильщица"
      },
      {
        "dir": 1,
        "pos": [
          22,
          1,
          99
        ],
        "text": "зарубание"
      },
      {
        "dir": 3,
        "pos": [
          2,
          13,
          93
        ],
        "text": "примерочная"
      },
      {
        "dir": 1,
        "pos": [
          13,
          20,
          97
        ],
        "text": "усыпление"
      },
      {
        "dir": 3,
        "pos": [
          23,
          19,
          87
        ],
        "text": "маринование"
      },
      {
        "dir": 1,
        "pos": [
          8,
          13,
          88
        ],
        "text": "сахармедович"
      },
      {
        "dir": 1,
        "pos": [
          29,
          18,
          90
        ],
        "text": "обандероление"
      },
      {
        "dir": 3,
        "pos": [
          11,
          5,
          89
        ],
        "text": "взрыватель"
      },
      {
        "dir": 1,
        "pos": [
          23,
          20,
          94
        ],
        "text": "регистратура"
      },
      {
        "dir": 3,
        "pos": [
          29,
          10,
          32
        ],
        "text": "растаптывание"
      },
      {
        "dir": 3,
        "pos": [
          8,
          5,
          82
        ],
        "text": "самоуважение"
      },
      {
        "dir": 1,
        "pos": [
          14,
          26,
          99
        ],
        "text": "купеляция"
      },
      {
        "dir": 1,
        "pos": [
          19,
          15,
          99
        ],
        "text": "клювонос"
      },
      {
        "dir": 3,
        "pos": [
          7,
          17,
          97
        ],
        "text": "хмурость"
      },
      {
        "dir": 2,
        "pos": [
          14,
          0,
          40
        ],
        "text": "низвергатель"
      },
      {
        "dir": 3,
        "pos": [
          14,
          4,
          87
        ],
        "text": "прицельность"
      },
      {
        "dir": 3,
        "pos": [
          9,
          16,
          76
        ],
        "text": "выстраданность"
      },
      {
        "dir": 1,
        "pos": [
          4,
          24,
          95
        ],
        "text": "буксировщик"
      },
      {
        "dir": 1,
        "pos": [
          26,
          5,
          94
        ],
        "text": "клептомания"
      },
      {
        "dir": 1,
        "pos": [
          4,
          11,
          93
        ],
        "text": "плоскогорье"
      },
      {
        "dir": 1,
        "pos": [
          26,
          12,
          94
        ],
        "text": "скирдование"
      },
      {
        "dir": 2,
        "pos": [
          18,
          3,
          85
        ],
        "text": "прокапывание"
      },
      {
        "dir": 1,
        "pos": [
          8,
          6,
          90
        ],
        "text": "амальгамация"
      },
      {
        "dir": 3,
        "pos": [
          0,
          0,
          57
        ],
        "text": "хладостойкость"
      },
      {
        "dir": 2,
        "pos": [
          12,
          15,
          99
        ],
        "text": "подставка"
      },
      {
        "dir": 2,
        "pos": [
          1,
          9,
          95
        ],
        "text": "перекрутка"
      },
      {
        "dir": 3,
        "pos": [
          29,
          19,
          66
        ],
        "text": "амальгама"
      },
      {
        "dir": 3,
        "pos": [
          24,
          0,
          82
        ],
        "text": "горнорабочий"
      },
      {
        "dir": 3,
        "pos": [
          26,
          3,
          96
        ],
        "text": "соискатель"
      },
      {
        "dir": 1,
        "pos": [
          0,
          4,
          54
        ],
        "text": "многопрограммность"
      },
      {
        "dir": 1,
        "pos": [
          13,
          4,
          99
        ],
        "text": "проточина"
      },
      {
        "dir": 1,
        "pos": [
          27,
          12,
          80
        ],
        "text": "минерализация"
      },
      {
        "dir": 1,
        "pos": [
          23,
          16,
          89
        ],
        "text": "искроуловитель"
      },
      {
        "dir": 1,
        "pos": [
          25,
          21,
          13
        ],
        "text": "сонаследница"
      },
      {
        "dir": 3,
        "pos": [
          29,
          21,
          34
        ],
        "text": "посыльная"
      },
      {
        "dir": 1,
        "pos": [
          4,
          20,
          97
        ],
        "text": "стогометание"
      },
      {
        "dir": 1,
        "pos": [
          16,
          28,
          89
        ],
        "text": "второклассница"
      },
      {
        "dir": 2,
        "pos": [
          2,
          2,
          89
        ],
        "text": "черноголовник"
      },
      {
        "dir": 1,
        "pos": [
          12,
          0,
          96
        ],
        "text": "разглаживание"
      },
      {
        "dir": 2,
        "pos": [
          12,
          20,
          86
        ],
        "text": "норднордвест"
      },
      {
        "dir": 3,
        "pos": [
          8,
          0,
          84
        ],
        "text": "ляпислазурь"
      },
      {
        "dir": 1,
        "pos": [
          23,
          17,
          62
        ],
        "text": "мобилизованность"
      },
      {
        "dir": 1,
        "pos": [
          0,
          5,
          14
        ],
        "text": "отоларинголог"
      },
      {
        "dir": 1,
        "pos": [
          4,
          13,
          89
        ],
        "text": "невропатолог"
      },
      {
        "dir": 1,
        "pos": [
          9,
          27,
          97
        ],
        "text": "беспомощность"
      },
      {
        "dir": 1,
        "pos": [
          17,
          21,
          97
        ],
        "text": "поспешность"
      },
      {
        "dir": 3,
        "pos": [
          26,
          8,
          99
        ],
        "text": "монетаризм"
      },
      {
        "dir": 1,
        "pos": [
          7,
          21,
          99
        ],
        "text": "дрожечник"
      },
      {
        "dir": 1,
        "pos": [
          16,
          17,
          76
        ],
        "text": "подстораживание"
      },
      {
        "dir": 3,
        "pos": [
          29,
          16,
          61
        ],
        "text": "приклеивание"
      },
      {
        "dir": 3,
        "pos": [
          21,
          20,
          93
        ],
        "text": "прилистник"
      },
      {
        "dir": 1,
        "pos": [
          2,
          24,
          90
        ],
        "text": "переплывание"
      },
      {
        "dir": 1,
        "pos": [
          9,
          20,
          83
        ],
        "text": "этикетировщик"
      },
      {
        "dir": 3,
        "pos": [
          2,
          0,
          91
        ],
        "text": "карбованец"
      },
      {
        "dir": 1,
        "pos": [
          6,
          6,
          86
        ],
        "text": "благоразумность"
      },
      {
        "dir": 1,
        "pos": [
          18,
          18,
          90
        ],
        "text": "дублирование"
      },
      {
        "dir": 1,
        "pos": [
          9,
          21,
          99
        ],
        "text": "сдвигание"
      },
      {
        "dir": 1,
        "pos": [
          0,
          13,
          95
        ],
        "text": "радиальность"
      },
      {
        "dir": 2,
        "pos": [
          6,
          11,
          98
        ],
        "text": "парусина"
      },
      {
        "dir": 2,
        "pos": [
          2,
          0,
          89
        ],
        "text": "японоведение"
      },
      {
        "dir": 3,
        "pos": [
          0,
          3,
          54
        ],
        "text": "хмурость"
      },
      {
        "dir": 3,
        "pos": [
          25,
          13,
          85
        ],
        "text": "разбросанность"
      },
      {
        "dir": 2,
        "pos": [
          19,
          13,
          97
        ],
        "text": "поликлиника"
      },
      {
        "dir": 3,
        "pos": [
          23,
          8,
          32
        ],
        "text": "безлюдность"
      },
      {
        "dir": 1,
        "pos": [
          0,
          0,
          12
        ],
        "text": "расшлихтовщик"
      },
      {
        "dir": 2,
        "pos": [
          13,
          29,
          91
        ],
        "text": "плесневение"
      },
      {
        "dir": 1,
        "pos": [
          4,
          6,
          99
        ],
        "text": "концентрирование"
      },
      {
        "dir": 1,
        "pos": [
          28,
          28,
          10
        ],
        "text": "плавильщица"
      },
      {
        "dir": 2,
        "pos": [
          17,
          29,
          95
        ],
        "text": "предвкушение"
      },
      {
        "dir": 1,
        "pos": [
          0,
          3,
          19
        ],
        "text": "удовлетворительность"
      },
      {
        "dir": 2,
        "pos": [
          4,
          23,
          98
        ],
        "text": "песочница"
      },
      {
        "dir": 1,
        "pos": [
          16,
          28,
          99
        ],
        "text": "семявход"
      },
      {
        "dir": 1,
        "pos": [
          0,
          25,
          99
        ],
        "text": "подсвинок"
      },
      {
        "dir": 2,
        "pos": [
          9,
          19,
          99
        ],
        "text": "очкование"
      },
      {
        "dir": 3,
        "pos": [
          0,
          0,
          87
        ],
        "text": "аллопатия"
      },
      {
        "dir": 1,
        "pos": [
          10,
          1,
          99
        ],
        "text": "органоген"
      },
      {
        "dir": 1,
        "pos": [
          15,
          9,
          90
        ],
        "text": "переключение"
      },
      {
        "dir": 3,
        "pos": [
          8,
          13,
          84
        ],
        "text": "разбросанность"
      },
      {
        "dir": 3,
        "pos": [
          28,
          0,
          87
        ],
        "text": "мореходство"
      },
      {
        "dir": 2,
        "pos": [
          11,
          17,
          99
        ],
        "text": "палестра"
      },
      {
        "dir": 2,
        "pos": [
          0,
          6,
          85
        ],
        "text": "кардиолог"
      },
      {
        "dir": 1,
        "pos": [
          5,
          25,
          99
        ],
        "text": "свистение"
      },
      {
        "dir": 3,
        "pos": [
          20,
          11,
          99
        ],
        "text": "сумрачность"
      },
      {
        "dir": 1,
        "pos": [
          29,
          3,
          58
        ],
        "text": "перемасливание"
      },
      {
        "dir": 3,
        "pos": [
          0,
          0,
          19
        ],
        "text": "полунамёк"
      },
      {
        "dir": 1,
        "pos": [
          0,
          20,
          98
        ],
        "text": "этюдность"
      },
      {
        "dir": 1,
        "pos": [
          2,
          28,
          99
        ],
        "text": "теньковка"
      },
      {
        "dir": 1,
        "pos": [
          3,
          0,
          85
        ],
        "text": "неотступность"
      },
      {
        "dir": 3,
        "pos": [
          0,
          10,
          90
        ],
        "text": "землистость"
      },
      {
        "dir": 2,
        "pos": [
          1,
          6,
          98
        ],
        "text": "замощение"
      },
      {
        "dir": 1,
        "pos": [
          17,
          26,
          95
        ],
        "text": "раскладчица"
      },
      {
        "dir": 1,
        "pos": [
          25,
          24,
          91
        ],
        "text": "гастроскопия"
      },
      {
        "dir": 3,
        "pos": [
          6,
          8,
          85
        ],
        "text": "тушевальщик"
      },
      {
        "dir": 2,
        "pos": [
          16,
          1,
          86
        ],
        "text": "выкидывание"
      },
      {
        "dir": 1,
        "pos": [
          15,
          17,
          99
        ],
        "text": "слоевище"
      },
      {
        "dir": 1,
        "pos": [
          27,
          29,
          98
        ],
        "text": "эквивокация"
      },
      {
        "dir": 1,
        "pos": [
          21,
          14,
          87
        ],
        "text": "котонизация"
      },
      {
        "dir": 1,
        "pos": [
          19,
          24,
          93
        ],
        "text": "изгнанничество"
      },
      {
        "dir": 2,
        "pos": [
          1,
          0,
          81
        ],
        "text": "раскалывание"
      },
      {
        "dir": 3,
        "pos": [
          29,
          20,
          50
        ],
        "text": "свальщица"
      },
      {
        "dir": 1,
        "pos": [
          21,
          22,
          99
        ],
        "text": "зубробизон"
      },
      {
        "dir": 3,
        "pos": [
          22,
          7,
          95
        ],
        "text": "разрежение"
      },
      {
        "dir": 1,
        "pos": [
          6,
          1,
          99
        ],
        "text": "швейцарка"
      },
      {
        "dir": 2,
        "pos": [
          0,
          20,
          86
        ],
        "text": "поднебесье"
      },
      {
        "dir": 1,
        "pos": [
          21,
          24,
          93
        ],
        "text": "иглодержатель"
      },
      {
        "dir": 1,
        "pos": [
          10,
          7,
          99
        ],
        "text": "ветвление"
      },
      {
        "dir": 3,
        "pos": [
          23,
          16,
          17
        ],
        "text": "перегревание"
      },
      {
        "dir": 3,
        "pos": [
          12,
          4,
          84
        ],
        "text": "автономность"
      },
      {
        "dir": 3,
        "pos": [
          4,
          0,
          94
        ],
        "text": "продажность"
      },
      {
        "dir": 1,
        "pos": [
          25,
          22,
          85
        ],
        "text": "неизбывность"
      },
      {
        "dir": 1,
        "pos": [
          13,
          27,
          95
        ],
        "text": "этимологизация"
      },
      {
        "dir": 1,
        "pos": [
          17,
          11,
          99
        ],
        "text": "вваривание"
      },
      {
        "dir": 1,
        "pos": [
          18,
          9,
          99
        ],
        "text": "кооперация"
      },
      {
        "dir": 3,
        "pos": [
          0,
          8,
          94
        ],
        "text": "развратительница"
      },
      {
        "dir": 1,
        "pos": [
          24,
          5,
          98
        ],
        "text": "назревание"
      },
      {
        "dir": 2,
        "pos": [
          5,
          0,
          26
        ],
        "text": "популярность"
      },
      {
        "dir": 3,
        "pos": [
          18,
          1,
          93
        ],
        "text": "инструктаж"
      },
      {
        "dir": 3,
        "pos": [
          22,
          2,
          90
        ],
        "text": "помазанница"
      },
      {
        "dir": 3,
        "pos": [
          4,
          6,
          99
        ],
        "text": "кормилица"
      },
      {
        "dir": 2,
        "pos": [
          4,
          9,
          79
        ],
        "text": "происходившее"
      },
      {
        "dir": 1,
        "pos": [
          7,
          17,
          84
        ],
        "text": "газогенератор"
      },
      {
        "dir": 2,
        "pos": [
          8,
          13,
          83
        ],
        "text": "междоусобица"
      },
      {
        "dir": 1,
        "pos": [
          29,
          0,
          68
        ],
        "text": "бесхитростность"
      },
      {
        "dir": 2,
        "pos": [
          18,
          3,
          94
        ],
        "text": "обречённость"
      },
      {
        "dir": 3,
        "pos": [
          28,
          13,
          6
        ],
        "text": "контрабандист"
      },
      {
        "dir": 1,
        "pos": [
          17,
          23,
          99
        ],
        "text": "нефтесклад"
      },
      {
        "dir": 1,
        "pos": [
          0,
          10,
          71
        ],
        "text": "коммуникабельность"
      },
      {
        "dir": 1,
        "pos": [
          17,
          29,
          98
        ],
        "text": "стопорение"
      },
      {
        "dir": 2,
        "pos": [
          17,
          10,
          84
        ],
        "text": "выщербление"
      },
      {
        "dir": 2,
        "pos": [
          12,
          24,
          88
        ],
        "text": "разжимание"
      },
      {
        "dir": 1,
        "pos": [
          14,
          7,
          96
        ],
        "text": "земледелец"
      },
      {
        "dir": 1,
        "pos": [
          2,
          6,
          99
        ],
        "text": "расцветка"
      },
      {
        "dir": 1,
        "pos": [
          12,
          4,
          89
        ],
        "text": "раздваивание"
      },
      {
        "dir": 3,
        "pos": [
          0,
          0,
          66
        ],
        "text": "недостаточность"
      },
      {
        "dir": 1,
        "pos": [
          21,
          21,
          9
        ],
        "text": "штуковщица"
      },
      {
        "dir": 1,
        "pos": [
          11,
          20,
          83
        ],
        "text": "прирабатывание"
      },
      {
        "dir": 1,
        "pos": [
          29,
          24,
          66
        ],
        "text": "гражданственность"
      },
      {
        "dir": 3,
        "pos": [
          17,
          14,
          91
        ],
        "text": "двусемянка"
      },
      {
        "dir": 2,
        "pos": [
          5,
          22,
          86
        ],
        "text": "правильщица"
      },
      {
        "dir": 2,
        "pos": [
          0,
          22,
          79
        ],
        "text": "неторопливость"
      },
      {
        "dir": 3,
        "pos": [
          2,
          5,
          89
        ],
        "text": "заковывание"
      },
      {
        "dir": 2,
        "pos": [
          0,
          4,
          80
        ],
        "text": "самодисциплина"
      },
      {
        "dir": 2,
        "pos": [
          10,
          4,
          93
        ],
        "text": "перитонит"
      },
      {
        "dir": 1,
        "pos": [
          8,
          20,
          96
        ],
        "text": "элитарность"
      },
      {
        "dir": 1,
        "pos": [
          11,
          29,
          97
        ],
        "text": "обтрясание"
      },
      {
        "dir": 3,
        "pos": [
          23,
          18,
          85
        ],
        "text": "изумлённость"
      },
      {
        "dir": 1,
        "pos": [
          29,
          15,
          88
        ],
        "text": "предгрозовье"
      },
      {
        "dir": 1,
        "pos": [
          14,
          2,
          94
        ],
        "text": "безрукавка"
      },
      {
        "dir": 1,
        "pos": [
          15,
          1,
          99
        ],
        "text": "достояние"
      },
      {
        "dir": 1,
        "pos": [
          25,
          20,
          94
        ],
        "text": "гидравлика"
      },
      {
        "dir": 1,
        "pos": [
          2,
          11,
          99
        ],
        "text": "параллель"
      },
      {
        "dir": 2,
        "pos": [
          2,
          24,
          90
        ],
        "text": "персонализм"
      },
      {
        "dir": 2,
        "pos": [
          7,
          17,
          84
        ],
        "text": "гротмарсель"
      },
      {
        "dir": 1,
        "pos": [
          27,
          16,
          88
        ],
        "text": "оплёскивание"
      },
      {
        "dir": 2,
        "pos": [
          14,
          26,
          97
        ],
        "text": "промыливание"
      },
      {
        "dir": 2,
        "pos": [
          16,
          12,
          79
        ],
        "text": "грассирование"
      },
      {
        "dir": 3,
        "pos": [
          19,
          14,
          98
        ],
        "text": "климатотерапия"
      },
      {
        "dir": 1,
        "pos": [
          10,
          0,
          90
        ],
        "text": "семидесятник"
      },
      {
        "dir": 3,
        "pos": [
          25,
          18,
          81
        ],
        "text": "нафабривание"
      },
      {
        "dir": 3,
        "pos": [
          6,
          6,
          99
        ],
        "text": "подчистка"
      },
      {
        "dir": 2,
        "pos": [
          0,
          0,
          85
        ],
        "text": "планетоведение"
      },
      {
        "dir": 1,
        "pos": [
          14,
          12,
          94
        ],
        "text": "листоблошка"
      },
      {
        "dir": 1,
        "pos": [
          22,
          18,
          99
        ],
        "text": "твёрдость"
      },
      {
        "dir": 1,
        "pos": [
          15,
          20,
          98
        ],
        "text": "прорабская"
      },
      {
        "dir": 1,
        "pos": [
          4,
          0,
          94
        ],
        "text": "предмостье"
      },
      {
        "dir": 3,
        "pos": [
          23,
          8,
          47
        ],
        "text": "прессовальня"
      },
      {
        "dir": 2,
        "pos": [
          1,
          17,
          89
        ],
        "text": "физиономистика"
      },
      {
        "dir": 1,
        "pos": [
          13,
          25,
          99
        ],
        "text": "египтянин"
      },
      {
        "dir": 1,
        "pos": [
          6,
          6,
          99
        ],
        "text": "перевивка"
      },
      {
        "dir": 3,
        "pos": [
          24,
          5,
          93
        ],
        "text": "воркование"
      },
      {
        "dir": 2,
        "pos": [
          13,
          20,
          96
        ],
        "text": "сводничание"
      },
      {
        "dir": 1,
        "pos": [
          6,
          13,
          89
        ],
        "text": "кустарничество"
      },
      {
        "dir": 1,
        "pos": [
          26,
          10,
          99
        ],
        "text": "наместник"
      },
      {
        "dir": 2,
        "pos": [
          0,
          15,
          98
        ],
        "text": "монархизм"
      },
      {
        "dir": 1,
        "pos": [
          8,
          13,
          99
        ],
        "text": "репатриант"
      },
      {
        "dir": 2,
        "pos": [
          7,
          23,
          95
        ],
        "text": "сплёвывание"
      },
      {
        "dir": 3,
        "pos": [
          28,
          11,
          99
        ],
        "text": "промывальщица"
      },
      {
        "dir": 3,
        "pos": [
          5,
          16,
          81
        ],
        "text": "педантичность"
      },
      {
        "dir": 1,
        "pos": [
          29,
          24,
          99
        ],
        "text": "секретариат"
      },
      {
        "dir": 3,
        "pos": [
          29,
          21,
          83
        ],
        "text": "побережье"
      },
      {
        "dir": 1,
        "pos": [
          6,
          4,
          93
        ],
        "text": "выцеливание"
      },
      {
        "dir": 3,
        "pos": [
          7,
          15,
          81
        ],
        "text": "провоцирование"
      },
      {
        "dir": 1,
        "pos": [
          0,
          1,
          37
        ],
        "text": "правозаступничество"
      },
      {
        "dir": 3,
        "pos": [
          15,
          8,
          98
        ],
        "text": "разгибатель"
      },
      {
        "dir": 1,
        "pos": [
          29,
          26,
          50
        ],
        "text": "израсходованность"
      },
      {
        "dir": 2,
        "pos": [
          4,
          1,
          99
        ],
        "text": "дешифровка"
      },
      {
        "dir": 1,
        "pos": [
          11,
          17,
          99
        ],
        "text": "падчерица"
      },
      {
        "dir": 2,
        "pos": [
          1,
          29,
          90
        ],
        "text": "радиоантенна"
      },
      {
        "dir": 2,
        "pos": [
          0,
          28,
          79
        ],
        "text": "жизнеощущение"
      },
      {
        "dir": 3,
        "pos": [
          29,
          2,
          45
        ],
        "text": "переобсуждение"
      },
      {
        "dir": 1,
        "pos": [
          23,
          14,
          89
        ],
        "text": "чернорабочая"
      },
      {
        "dir": 3,
        "pos": [
          27,
          7,
          80
        ],
        "text": "хронометражист"
      },
      {
        "dir": 1,
        "pos": [
          6,
          27,
          97
        ],
        "text": "крольчатина"
      },
      {
        "dir": 3,
        "pos": [
          13,
          8,
          95
        ],
        "text": "бланшировка"
      },
      {
        "dir": 1,
        "pos": [
          25,
          0,
          54
        ],
        "text": "несоразмерность"
      },
      {
        "dir": 1,
        "pos": [
          13,
          17,
          89
        ],
        "text": "кинохроника"
      },
      {
        "dir": 1,
        "pos": [
          16,
          7,
          99
        ],
        "text": "гранддама"
      },
      {
        "dir": 1,
        "pos": [
          6,
          24,
          94
        ],
        "text": "психометрия"
      },
      {
        "dir": 1,
        "pos": [
          8,
          4,
          99
        ],
        "text": "белодеревец"
      },
      {
        "dir": 3,
        "pos": [
          15,
          14,
          94
        ],
        "text": "комиссарство"
      },
      {
        "dir": 3,
        "pos": [
          26,
          0,
          87
        ],
        "text": "миллиардер"
      },
      {
        "dir": 3,
        "pos": [
          20,
          2,
          92
        ],
        "text": "коноплянка"
      },
      {
        "dir": 1,
        "pos": [
          8,
          2,
          87
        ],
        "text": "пропудривание"
      },
      {
        "dir": 2,
        "pos": [
          16,
          11,
          97
        ],
        "text": "самозванец"
      },
      {
        "dir": 3,
        "pos": [
          8,
          3,
          92
        ],
        "text": "детектирование"
      },
      {
        "dir": 2,
        "pos": [
          15,
          22,
          83
        ],
        "text": "выскакивание"
      },
      {
        "dir": 3,
        "pos": [
          27,
          17,
          91
        ],
        "text": "пигментация"
      },
      {
        "dir": 1,
        "pos": [
          5,
          22,
          86
        ],
        "text": "паразитология"
      },
      {
        "dir": 3,
        "pos": [
          10,
          14,
          88
        ],
        "text": "развеивание"
      },
      {
        "dir": 3,
        "pos": [
          19,
          19,
          93
        ],
        "text": "релятивист"
      },
      {
        "dir": 2,
        "pos": [
          20,
          20,
          91
        ],
        "text": "полихромия"
      },
      {
        "dir": 1,
        "pos": [
          2,
          17,
          94
        ],
        "text": "дератизация"
      },
      {
        "dir": 1,
        "pos": [
          12,
          13,
          88
        ],
        "text": "пересортировка"
      },
      {
        "dir": 1,
        "pos": [
          2,
          0,
          99
        ],
        "text": "бутафорская"
      },
      {
        "dir": 1,
        "pos": [
          24,
          3,
          92
        ],
        "text": "опрокидывание"
      },
      {
        "dir": 1,
        "pos": [
          26,
          16,
          99
        ],
        "text": "заливание"
      },
      {
        "dir": 2,
        "pos": [
          14,
          28,
          87
        ],
        "text": "профилактика"
      },
      {
        "dir": 2,
        "pos": [
          16,
          0,
          49
        ],
        "text": "подсчитывание"
      },
      {
        "dir": 3,
        "pos": [
          29,
          0,
          68
        ],
        "text": "богослужение"
      },
      {
        "dir": 1,
        "pos": [
          23,
          26,
          99
        ],
        "text": "кантианец"
      },
      {
        "dir": 3,
        "pos": [
          28,
          8,
          89
        ],
        "text": "крутоверть"
      },
      {
        "dir": 2,
        "pos": [
          13,
          4,
          99
        ],
        "text": "приспособляемость"
      },
      {
        "dir": 2,
        "pos": [
          5,
          1,
          97
        ],
        "text": "непригодность"
      },
      {
        "dir": 3,
        "pos": [
          0,
          8,
          85
        ],
        "text": "гигантомания"
      },
      {
        "dir": 1,
        "pos": [
          1,
          29,
          97
        ],
        "text": "мандатарий"
      },
      {
        "dir": 3,
        "pos": [
          28,
          3,
          81
        ],
        "text": "защищённость"
      },
      {
        "dir": 1,
        "pos": [
          16,
          0,
          40
        ],
        "text": "заколдованность"
      },
      {
        "dir": 2,
        "pos": [
          4,
          27,
          94
        ],
        "text": "палимпсест"
      },
      {
        "dir": 1,
        "pos": [
          29,
          23,
          83
        ],
        "text": "безотносительность"
      },
      {
        "dir": 2,
        "pos": [
          4,
          17,
          91
        ],
        "text": "обвяливание"
      },
      {
        "dir": 3,
        "pos": [
          4,
          13,
          89
        ],
        "text": "неофициальность"
      },
      {
        "dir": 3,
        "pos": [
          2,
          18,
          95
        ],
        "text": "израильтянка"
      },
      {
        "dir": 1,
        "pos": [
          13,
          6,
          79
        ],
        "text": "хладостойкость"
      },
      {
        "dir": 3,
        "pos": [
          20,
          2,
          96
        ],
        "text": "подмуровка"
      },
      {
        "dir": 1,
        "pos": [
          20,
          18,
          99
        ],
        "text": "одногодок"
      },
      {
        "dir": 3,
        "pos": [
          13,
          11,
          99
        ],
        "text": "звукоулавливатель"
      },
      {
        "dir": 3,
        "pos": [
          28,
          5,
          92
        ],
        "text": "льноочиститель"
      },
      {
        "dir": 1,
        "pos": [
          0,
          28,
          89
        ],
        "text": "вышкомонтажник"
      },
      {
        "dir": 3,
        "pos": [
          0,
          21,
          99
        ],
        "text": "рецептура"
      },
      {
        "dir": 1,
        "pos": [
          28,
          14,
          92
        ],
        "text": "изрезанность"
      },
      {
        "dir": 3,
        "pos": [
          23,
          11,
          89
        ],
        "text": "ворчливость"
      },
      {
        "dir": 3,
        "pos": [
          11,
          8,
          98
        ],
        "text": "полимеризация"
      },
      {
        "dir": 1,
        "pos": [
          2,
          4,
          74
        ],
        "text": "засматривание"
      },
      {
        "dir": 1,
        "pos": [
          19,
          12,
          96
        ],
        "text": "тушевальщик"
      },
      {
        "dir": 3,
        "pos": [
          0,
          3,
          81
        ],
        "text": "подсаживание"
      },
      {
        "dir": 1,
        "pos": [
          23,
          29,
          95
        ],
        "text": "увеселительница"
      },
      {
        "dir": 2,
        "pos": [
          15,
          17,
          62
        ],
        "text": "непокоримость"
      },
      {
        "dir": 3,
        "pos": [
          4,
          8,
          86
        ],
        "text": "фотогравюра"
      },
      {
        "dir": 2,
        "pos": [
          19,
          29,
          97
        ],
        "text": "сервировка"
      },
      {
        "dir": 2,
        "pos": [
          19,
          14,
          87
        ],
        "text": "сокурсница"
      },
      {
        "dir": 1,
        "pos": [
          2,
          13,
          95
        ],
        "text": "эсперантист"
      },
      {
        "dir": 1,
        "pos": [
          12,
          9,
          88
        ],
        "text": "пустозёрница"
      },
      {
        "dir": 1,
        "pos": [
          15,
          29,
          97
        ],
        "text": "кондитерша"
      },
      {
        "dir": 3,
        "pos": [
          20,
          14,
          89
        ],
        "text": "проминание"
      },
      {
        "dir": 2,
        "pos": [
          6,
          20,
          79
        ],
        "text": "перемазывание"
      },
      {
        "dir": 1,
        "pos": [
          23,
          21,
          18
        ],
        "text": "преждевременность"
      },
      {
        "dir": 2,
        "pos": [
          1,
          28,
          98
        ],
        "text": "перековеркивание"
      },
      {
        "dir": 1,
        "pos": [
          0,
          0,
          99
        ],
        "text": "комбинаторика"
      },
      {
        "dir": 3,
        "pos": [
          22,
          0,
          92
        ],
        "text": "лингвистика"
      },
      {
        "dir": 3,
        "pos": [
          2,
          13,
          99
        ],
        "text": "звукопроводимость"
      },
      {
        "dir": 2,
        "pos": [
          16,
          3,
          83
        ],
        "text": "пассерование"
      },
      {
        "dir": 3,
        "pos": [
          23,
          19,
          99
        ],
        "text": "кронциркуль"
      },
      {
        "dir": 1,
        "pos": [
          4,
          22,
          97
        ],
        "text": "должность"
      },
      {
        "dir": 1,
        "pos": [
          0,
          15,
          99
        ],
        "text": "смывщица"
      },
      {
        "dir": 1,
        "pos": [
          11,
          10,
          99
        ],
        "text": "гладильщица"
      },
      {
        "dir": 2,
        "pos": [
          13,
          3,
          81
        ],
        "text": "загораживание"
      },
      {
        "dir": 1,
        "pos": [
          0,
          6,
          66
        ],
        "text": "автодиспетчер"
      },
      {
        "dir": 3,
        "pos": [
          17,
          10,
          96
        ],
        "text": "кристалличность"
      },
      {
        "dir": 1,
        "pos": [
          10,
          17,
          89
        ],
        "text": "свойственница"
      },
      {
        "dir": 2,
        "pos": [
          18,
          1,
          84
        ],
        "text": "самоучитель"
      },
      {
        "dir": 1,
        "pos": [
          4,
          13,
          99
        ],
        "text": "церемония"
      },
      {
        "dir": 2,
        "pos": [
          13,
          7,
          88
        ],
        "text": "первоисточник"
      },
      {
        "dir": 3,
        "pos": [
          0,
          0,
          99
        ],
        "text": "коммуникабельность"
      },
      {
        "dir": 1,
        "pos": [
          28,
          23,
          20
        ],
        "text": "парафразирование"
      },
      {
        "dir": 3,
        "pos": [
          28,
          21,
          0
        ],
        "text": "фактограф"
      },
      {
        "dir": 1,
        "pos": [
          4,
          4,
          99
        ],
        "text": "завещатель"
      },
      {
        "dir": 2,
        "pos": [
          2,
          4,
          91
        ],
        "text": "облицовщик"
      },
      {
        "dir": 1,
        "pos": [
          29,
          13,
          45
        ],
        "text": "неправомерность"
      },
      {
        "dir": 1,
        "pos": [
          4,
          29,
          95
        ],
        "text": "историчность"
      },
      {
        "dir": 1,
        "pos": [
          0,
          27,
          99
        ],
        "text": "уезжающая"
      },
      {
        "dir": 1,
        "pos": [
          23,
          18,
          47
        ],
        "text": "неплодотворность"
      },
      {
        "dir": 1,
        "pos": [
          18,
          7,
          99
        ],
        "text": "расшаркивание"
      },
      {
        "dir": 3,
        "pos": [
          27,
          16,
          87
        ],
        "text": "пульпопровод"
      },
      {
        "dir": 2,
        "pos": [
          0,
          4,
          96
        ],
        "text": "сентенциозность"
      },
      {
        "dir": 1,
        "pos": [
          23,
          12,
          83
        ],
        "text": "лжетолкование"
      },
      {
        "dir": 2,
        "pos": [
          6,
          24,
          86
        ],
        "text": "разрушитель"
      },
      {
        "dir": 2,
        "pos": [
          0,
          4,
          53
        ],
        "text": "набивальщица"
      },
      {
        "dir": 2,
        "pos": [
          16,
          26,
          89
        ],
        "text": "однозернянка"
      },
      {
        "dir": 2,
        "pos": [
          9,
          6,
          75
        ],
        "text": "вероотступник"
      },
      {
        "dir": 3,
        "pos": [
          0,
          0,
          3
        ],
        "text": "выворотность"
      },
      {
        "dir": 3,
        "pos": [
          29,
          18,
          89
        ],
        "text": "бронестекло"
      },
      {
        "dir": 1,
        "pos": [
          4,
          15,
          94
        ],
        "text": "христосование"
      },
      {
        "dir": 1,
        "pos": [
          2,
          25,
          99
        ],
        "text": "монотеист"
      },
      {
        "dir": 1,
        "pos": [
          12,
          0,
          26
        ],
        "text": "несвариваемость"
      },
      {
        "dir": 1,
        "pos": [
          0,
          4,
          99
        ],
        "text": "увеселение"
      },
      {
        "dir": 1,
        "pos": [
          28,
          11,
          99
        ],
        "text": "подгонщик"
      },
      {
        "dir": 1,
        "pos": [
          25,
          29,
          98
        ],
        "text": "модератор"
      },
      {
        "dir": 2,
        "pos": [
          20,
          1,
          95
        ],
        "text": "добродушие"
      },
      {
        "dir": 2,
        "pos": [
          2,
          20,
          90
        ],
        "text": "затворница"
      },
      {
        "dir": 3,
        "pos": [
          22,
          1,
          97
        ],
        "text": "режиссирование"
      },
      {
        "dir": 3,
        "pos": [
          6,
          17,
          88
        ],
        "text": "инопланетянин"
      },
      {
        "dir": 1,
        "pos": [
          0,
          11,
          88
        ],
        "text": "обмачивание"
      },
      {
        "dir": 1,
        "pos": [
          28,
          7,
          99
        ],
        "text": "пришивание"
      },
      {
        "dir": 1,
        "pos": [
          24,
          9,
          99
        ],
        "text": "негибкость"
      },
      {
        "dir": 2,
        "pos": [
          9,
          20,
          83
        ],
        "text": "эмпириокритик"
      },
      {
        "dir": 3,
        "pos": [
          5,
          16,
          83
        ],
        "text": "отвлекаемость"
      },
      {
        "dir": 3,
        "pos": [
          0,
          9,
          88
        ],
        "text": "опознавание"
      },
      {
        "dir": 1,
        "pos": [
          19,
          1,
          92
        ],
        "text": "замасливание"
      },
      {
        "dir": 3,
        "pos": [
          29,
          9,
          80
        ],
        "text": "разжалование"
      },
      {
        "dir": 3,
        "pos": [
          0,
          2,
          71
        ],
        "text": "натравщик"
      },
      {
        "dir": 1,
        "pos": [
          20,
          16,
          95
        ],
        "text": "несытность"
      },
      {
        "dir": 3,
        "pos": [
          2,
          18,
          81
        ],
        "text": "затерянность"
      },
      {
        "dir": 3,
        "pos": [
          0,
          0,
          10
        ],
        "text": "сюрреалист"
      },
      {
        "dir": 3,
        "pos": [
          6,
          9,
          93
        ],
        "text": "бугристость"
      },
      {
        "dir": 2,
        "pos": [
          8,
          2,
          87
        ],
        "text": "припаивание"
      },
      {
        "dir": 3,
        "pos": [
          13,
          17,
          83
        ],
        "text": "онаречивание"
      },
      {
        "dir": 2,
        "pos": [
          5,
          29,
          97
        ],
        "text": "окулировщик"
      },
      {
        "dir": 3,
        "pos": [
          0,
          5,
          14
        ],
        "text": "одноплеменник"
      },
      {
        "dir": 1,
        "pos": [
          25,
          28,
          89
        ],
        "text": "правильщица"
      },
      {
        "dir": 2,
        "pos": [
          20,
          16,
          97
        ],
        "text": "мондиалист"
      },
      {
        "dir": 1,
        "pos": [
          21,
          12,
          88
        ],
        "text": "прокламация"
      },
      {
        "dir": 3,
        "pos": [
          0,
          15,
          83
        ],
        "text": "шёлкоткачество"
      },
      {
        "dir": 2,
        "pos": [
          17,
          18,
          98
        ],
        "text": "угадывание"
      }
    ]
  }
}