{
  "doneTowers": [
    {
      "id": 0,
      "score": 3072830.45
    },
    {
      "id": 0,
      "score": 3247312.43
    },
    {
      "id": 1,
      "score": 3221193.33
    },
    {
      "id": 2,
      "score": 3136144.27
    }
  ],
  "score": 13229603.1,
  "tower": {
    "score": 552122.62,
    "words": [
      {
        "dir": 1,
        "pos": [
          17,
          11,
          97
        ],
        "text": "эпохальность"
      },
      {
        "dir": 1,
        "pos": [
          1,
          5,
          77
        ],
        "text": "сверхъестественность"
      },
      {
        "dir": 1,
        "pos": [
          9,
          3,
          99
        ],
        "text": "отвлекаемость"
      },
      {
        "dir": 1,
        "pos": [
          1,
          9,
          54
        ],
        "text": "шёлкопрядильщица"
      },
      {
        "dir": 2,
        "pos": [
          9,
          7,
          99
        ],
        "text": "макрофотография"
      },
      {
        "dir": 1,
        "pos": [
          1,
          5,
          99
        ],
        "text": "побледнение"
      },
      {
        "dir": 1,
        "pos": [
          23,
          26,
          99
        ],
        "text": "обравнивание"
      },
      {
        "dir": 1,
        "pos": [
          13,
          18,
          99
        ],
        "text": "притопывание"
      },
      {
        "dir": 2,
        "pos": [
          1,
          22,
          98
        ],
        "text": "впрыскивание"
      },
      {
        "dir": 1,
        "pos": [
          7,
          16,
          94
        ],
        "text": "бесцеремонность"
      },
      {
        "dir": 1,
        "pos": [
          11,
          18,
          99
        ],
        "text": "гравиметрист"
      },
      {
        "dir": 1,
        "pos": [
          19,
          21,
          98
        ],
        "text": "содержательность"
      },
      {
        "dir": 1,
        "pos": [
          1,
          7,
          58
        ],
        "text": "одиннадцатиклассник"
      },
      {
        "dir": 1,
        "pos": [
          20,
          11,
          99
        ],
        "text": "подразделение"
      },
      {
        "dir": 2,
        "pos": [
          16,
          0,
          90
        ],
        "text": "деблокирование"
      },
      {
        "dir": 1,
        "pos": [
          29,
          23,
          99
        ],
        "text": "неподкованность"
      },
      {
        "dir": 3,
        "pos": [
          11,
          11,
          95
        ],
        "text": "энигматичность"
      },
      {
        "dir": 3,
        "pos": [
          25,
          16,
          99
        ],
        "text": "замораживание"
      },
      {
        "dir": 1,
        "pos": [
          27,
          26,
          97
        ],
        "text": "нецелесообразность"
      },
      {
        "dir": 1,
        "pos": [
          29,
          26,
          95
        ],
        "text": "вышкостроитель"
      },
      {
        "dir": 1,
        "pos": [
          1,
          7,
          99
        ],
        "text": "сократительность"
      },
      {
        "dir": 1,
        "pos": [
          20,
          2,
          98
        ],
        "text": "хроникальность"
      },
      {
        "dir": 3,
        "pos": [
          15,
          11,
          88
        ],
        "text": "почтительность"
      },
      {
        "dir": 3,
        "pos": [
          3,
          0,
          98
        ],
        "text": "радиоустановка"
      },
      {
        "dir": 2,
        "pos": [
          8,
          26,
          87
        ],
        "text": "сальтоморталист"
      },
      {
        "dir": 2,
        "pos": [
          3,
          29,
          98
        ],
        "text": "социолингвистика"
      },
      {
        "dir": 1,
        "pos": [
          1,
          3,
          95
        ],
        "text": "освидетельствование"
      },
      {
        "dir": 1,
        "pos": [
          5,
          15,
          99
        ],
        "text": "переживание"
      },
      {
        "dir": 1,
        "pos": [
          14,
          0,
          99
        ],
        "text": "небережливость"
      },
      {
        "dir": 3,
        "pos": [
          1,
          5,
          99
        ],
        "text": "пустынножительница"
      },
      {
        "dir": 1,
        "pos": [
          9,
          13,
          99
        ],
        "text": "полегаемость"
      },
      {
        "dir": 1,
        "pos": [
          29,
          21,
          99
        ],
        "text": "плевательница"
      },
      {
        "dir": 3,
        "pos": [
          3,
          16,
          99
        ],
        "text": "шёлкоткачество"
      },
      {
        "dir": 1,
        "pos": [
          27,
          13,
          99
        ],
        "text": "выклёвывание"
      },
      {
        "dir": 1,
        "pos": [
          1,
          26,
          99
        ],
        "text": "тяжелораненый"
      },
      {
        "dir": 2,
        "pos": [
          7,
          26,
          99
        ],
        "text": "приобретательство"
      },
      {
        "dir": 2,
        "pos": [
          3,
          0,
          9
        ],
        "text": "корригирование"
      },
      {
        "dir": 1,
        "pos": [
          3,
          18,
          97
        ],
        "text": "неудобоваримость"
      },
      {
        "dir": 3,
        "pos": [
          13,
          8,
          97
        ],
        "text": "спрыскивание"
      },
      {
        "dir": 3,
        "pos": [
          7,
          3,
          99
        ],
        "text": "гелертерство"
      },
      {
        "dir": 1,
        "pos": [
          9,
          24,
          99
        ],
        "text": "малоудойность"
      },
      {
        "dir": 1,
        "pos": [
          13,
          3,
          99
        ],
        "text": "припрядывание"
      },
      {
        "dir": 1,
        "pos": [
          23,
          18,
          99
        ],
        "text": "виртуальность"
      },
      {
        "dir": 1,
        "pos": [
          3,
          29,
          99
        ],
        "text": "оскабливание"
      },
      {
        "dir": 2,
        "pos": [
          16,
          26,
          84
        ],
        "text": "предвосхищение"
      },
      {
        "dir": 1,
        "pos": [
          25,
          24,
          99
        ],
        "text": "выколашивание"
      },
      {
        "dir": 3,
        "pos": [
          27,
          1,
          97
        ],
        "text": "прямоугольник"
      },
      {
        "dir": 2,
        "pos": [
          0,
          0,
          0
        ],
        "text": "ледоисследователь"
      },
      {
        "dir": 2,
        "pos": [
          1,
          29,
          94
        ],
        "text": "голословность"
      },
      {
        "dir": 1,
        "pos": [
          25,
          21,
          99
        ],
        "text": "авиадесантник"
      },
      {
        "dir": 3,
        "pos": [
          5,
          0,
          96
        ],
        "text": "эффективность"
      },
      {
        "dir": 3,
        "pos": [
          20,
          0,
          88
        ],
        "text": "умопомрачение"
      },
      {
        "dir": 2,
        "pos": [
          16,
          13,
          89
        ],
        "text": "откупоривание"
      },
      {
        "dir": 1,
        "pos": [
          7,
          5,
          97
        ],
        "text": "подпечатывание"
      },
      {
        "dir": 1,
        "pos": [
          7,
          10,
          99
        ],
        "text": "рейдирование"
      },
      {
        "dir": 2,
        "pos": [
          1,
          7,
          93
        ],
        "text": "инвариантность"
      },
      {
        "dir": 3,
        "pos": [
          19,
          14,
          90
        ],
        "text": "обходительность"
      },
      {
        "dir": 1,
        "pos": [
          5,
          3,
          99
        ],
        "text": "скрещиваемость"
      },
      {
        "dir": 1,
        "pos": [
          29,
          0,
          99
        ],
        "text": "жизнеощущение"
      },
      {
        "dir": 1,
        "pos": [
          1,
          15,
          99
        ],
        "text": "термидорианец"
      },
      {
        "dir": 3,
        "pos": [
          3,
          8,
          86
        ],
        "text": "ссудоприниматель"
      },
      {
        "dir": 1,
        "pos": [
          20,
          4,
          96
        ],
        "text": "железнодорожница"
      },
      {
        "dir": 1,
        "pos": [
          9,
          26,
          91
        ],
        "text": "маниакальность"
      },
      {
        "dir": 2,
        "pos": [
          0,
          13,
          97
        ],
        "text": "столоначальник"
      },
      {
        "dir": 3,
        "pos": [
          1,
          0,
          21
        ],
        "text": "телелюбитель"
      },
      {
        "dir": 2,
        "pos": [
          16,
          8,
          92
        ],
        "text": "штабквартира"
      },
      {
        "dir": 2,
        "pos": [
          6,
          10,
          98
        ],
        "text": "демпфирование"
      },
      {
        "dir": 2,
        "pos": [
          15,
          6,
          86
        ],
        "text": "электроразведка"
      },
      {
        "dir": 3,
        "pos": [
          3,
          5,
          96
        ],
        "text": "патронодержатель"
      },
      {
        "dir": 1,
        "pos": [
          23,
          8,
          98
        ],
        "text": "теплопроводность"
      },
      {
        "dir": 3,
        "pos": [
          5,
          0,
          87
        ],
        "text": "притеснительница"
      },
      {
        "dir": 1,
        "pos": [
          9,
          5,
          99
        ],
        "text": "развинчивание"
      },
      {
        "dir": 1,
        "pos": [
          15,
          5,
          99
        ],
        "text": "пересинивание"
      },
      {
        "dir": 3,
        "pos": [
          1,
          0,
          95
        ],
        "text": "фотокерамика"
      },
      {
        "dir": 1,
        "pos": [
          1,
          11,
          40
        ],
        "text": "непрофессиональность"
      },
      {
        "dir": 3,
        "pos": [
          29,
          14,
          92
        ],
        "text": "ферросплавщик"
      },
      {
        "dir": 3,
        "pos": [
          15,
          3,
          94
        ],
        "text": "причерчивание"
      },
      {
        "dir": 3,
        "pos": [
          7,
          0,
          96
        ],
        "text": "воспроизведение"
      },
      {
        "dir": 1,
        "pos": [
          11,
          7,
          99
        ],
        "text": "корзиноплетение"
      },
      {
        "dir": 1,
        "pos": [
          15,
          23,
          95
        ],
        "text": "общедоступность"
      },
      {
        "dir": 2,
        "pos": [
          16,
          16,
          96
        ],
        "text": "максимилизация"
      },
      {
        "dir": 1,
        "pos": [
          18,
          5,
          99
        ],
        "text": "вдалбливание"
      },
      {
        "dir": 3,
        "pos": [
          1,
          18,
          92
        ],
        "text": "провинциалка"
      },
      {
        "dir": 2,
        "pos": [
          17,
          29,
          96
        ],
        "text": "застрачивание"
      },
      {
        "dir": 1,
        "pos": [
          26,
          19,
          98
        ],
        "text": "вертикальность"
      },
      {
        "dir": 1,
        "pos": [
          13,
          10,
          99
        ],
        "text": "сортирование"
      },
      {
        "dir": 2,
        "pos": [
          14,
          4,
          86
        ],
        "text": "неполноправность"
      },
      {
        "dir": 1,
        "pos": [
          3,
          1,
          99
        ],
        "text": "разветвление"
      },
      {
        "dir": 1,
        "pos": [
          9,
          7,
          99
        ],
        "text": "меркантильность"
      },
      {
        "dir": 1,
        "pos": [
          27,
          29,
          99
        ],
        "text": "разнотипность"
      },
      {
        "dir": 2,
        "pos": [
          14,
          0,
          99
        ],
        "text": "неустойчивость"
      },
      {
        "dir": 1,
        "pos": [
          11,
          3,
          97
        ],
        "text": "самоотравление"
      },
      {
        "dir": 3,
        "pos": [
          21,
          13,
          98
        ],
        "text": "деморализация"
      },
      {
        "dir": 3,
        "pos": [
          27,
          13,
          99
        ],
        "text": "вакцинотерапия"
      },
      {
        "dir": 1,
        "pos": [
          26,
          0,
          99
        ],
        "text": "томасирование"
      },
      {
        "dir": 2,
        "pos": [
          18,
          26,
          97
        ],
        "text": "вышпаривание"
      },
      {
        "dir": 2,
        "pos": [
          4,
          3,
          89
        ],
        "text": "тождественность"
      },
      {
        "dir": 2,
        "pos": [
          13,
          18,
          98
        ],
        "text": "романтизация"
      },
      {
        "dir": 2,
        "pos": [
          15,
          2,
          92
        ],
        "text": "подглаживание"
      },
      {
        "dir": 2,
        "pos": [
          18,
          29,
          93
        ],
        "text": "возбуждение"
      },
      {
        "dir": 1,
        "pos": [
          25,
          29,
          98
        ],
        "text": "освидетельствование"
      },
      {
        "dir": 1,
        "pos": [
          20,
          0,
          97
        ],
        "text": "самогонокурение"
      },
      {
        "dir": 3,
        "pos": [
          1,
          7,
          37
        ],
        "text": "перередактирование"
      },
      {
        "dir": 1,
        "pos": [
          20,
          6,
          90
        ],
        "text": "перерисовывание"
      },
      {
        "dir": 1,
        "pos": [
          7,
          20,
          99
        ],
        "text": "суверенность"
      },
      {
        "dir": 2,
        "pos": [
          15,
          11,
          99
        ],
        "text": "подкапчивание"
      },
      {
        "dir": 1,
        "pos": [
          25,
          11,
          99
        ],
        "text": "незаносчивость"
      },
      {
        "dir": 2,
        "pos": [
          1,
          1,
          85
        ],
        "text": "неэквивалентность"
      },
      {
        "dir": 1,
        "pos": [
          17,
          13,
          99
        ],
        "text": "выдуманность"
      },
      {
        "dir": 3,
        "pos": [
          1,
          7,
          30
        ],
        "text": "шёлкопрядильщик"
      },
      {
        "dir": 2,
        "pos": [
          14,
          21,
          91
        ],
        "text": "кислотоупорность"
      },
      {
        "dir": 3,
        "pos": [
          26,
          5,
          85
        ],
        "text": "благоприятность"
      },
      {
        "dir": 3,
        "pos": [
          1,
          0,
          58
        ],
        "text": "офтальмоскоп"
      },
      {
        "dir": 2,
        "pos": [
          14,
          19,
          86
        ],
        "text": "вспучиваемость"
      },
      {
        "dir": 1,
        "pos": [
          23,
          13,
          99
        ],
        "text": "форсирование"
      },
      {
        "dir": 2,
        "pos": [
          18,
          8,
          98
        ],
        "text": "прочитывание"
      },
      {
        "dir": 2,
        "pos": [
          1,
          26,
          93
        ],
        "text": "рациональность"
      },
      {
        "dir": 1,
        "pos": [
          26,
          6,
          94
        ],
        "text": "исключительность"
      },
      {
        "dir": 2,
        "pos": [
          10,
          0,
          97
        ],
        "text": "озлобленность"
      },
      {
        "dir": 3,
        "pos": [
          13,
          3,
          91
        ],
        "text": "воздержанность"
      },
      {
        "dir": 1,
        "pos": [
          23,
          21,
          96
        ],
        "text": "огнепоклонничество"
      },
      {
        "dir": 2,
        "pos": [
          9,
          5,
          97
        ],
        "text": "закупоривание"
      },
      {
        "dir": 1,
        "pos": [
          28,
          16,
          96
        ],
        "text": "импровизационность"
      },
      {
        "dir": 1,
        "pos": [
          3,
          22,
          99
        ],
        "text": "кредитование"
      },
      {
        "dir": 3,
        "pos": [
          17,
          11,
          94
        ],
        "text": "храмостроитель"
      },
      {
        "dir": 2,
        "pos": [
          1,
          1,
          99
        ],
        "text": "структурность"
      },
      {
        "dir": 1,
        "pos": [
          15,
          15,
          99
        ],
        "text": "катетеризация"
      },
      {
        "dir": 3,
        "pos": [
          11,
          2,
          91
        ],
        "text": "хронологизация"
      },
      {
        "dir": 3,
        "pos": [
          29,
          0,
          94
        ],
        "text": "отштамповывание"
      },
      {
        "dir": 3,
        "pos": [
          1,
          6,
          40
        ],
        "text": "эксцентризм"
      },
      {
        "dir": 3,
        "pos": [
          29,
          0,
          96
        ],
        "text": "незаконченность"
      },
      {
        "dir": 2,
        "pos": [
          4,
          20,
          98
        ],
        "text": "преуспевание"
      },
      {
        "dir": 3,
        "pos": [
          1,
          2,
          77
        ],
        "text": "неустанность"
      },
      {
        "dir": 3,
        "pos": [
          13,
          5,
          99
        ],
        "text": "прописывание"
      },
      {
        "dir": 2,
        "pos": [
          13,
          26,
          82
        ],
        "text": "коммуникативность"
      },
      {
        "dir": 3,
        "pos": [
          15,
          2,
          96
        ],
        "text": "перехварывание"
      },
      {
        "dir": 2,
        "pos": [
          16,
          11,
          95
        ],
        "text": "подмазывание"
      },
      {
        "dir": 1,
        "pos": [
          11,
          21,
          97
        ],
        "text": "просвечивание"
      },
      {
        "dir": 3,
        "pos": [
          29,
          15,
          99
        ],
        "text": "взаимопонимание"
      },
      {
        "dir": 2,
        "pos": [
          11,
          5,
          99
        ],
        "text": "оспопрививание"
      },
      {
        "dir": 1,
        "pos": [
          1,
          15,
          40
        ],
        "text": "звукопроводимость"
      },
      {
        "dir": 3,
        "pos": [
          25,
          1,
          96
        ],
        "text": "стандартизация"
      },
      {
        "dir": 2,
        "pos": [
          9,
          3,
          99
        ],
        "text": "обеспечивание"
      },
      {
        "dir": 2,
        "pos": [
          18,
          16,
          92
        ],
        "text": "гидромонитор"
      },
      {
        "dir": 3,
        "pos": [
          9,
          16,
          90
        ],
        "text": "эскарпирование"
      },
      {
        "dir": 3,
        "pos": [
          11,
          17,
          92
        ],
        "text": "этикетировщик"
      },
      {
        "dir": 1,
        "pos": [
          3,
          0,
          16
        ],
        "text": "подстрекательство"
      },
      {
        "dir": 2,
        "pos": [
          9,
          24,
          99
        ],
        "text": "монометаллизм"
      },
      {
        "dir": 1,
        "pos": [
          23,
          4,
          98
        ],
        "text": "обмеблировывание"
      },
      {
        "dir": 1,
        "pos": [
          5,
          5,
          98
        ],
        "text": "остервенелость"
      },
      {
        "dir": 1,
        "pos": [
          7,
          23,
          97
        ],
        "text": "пухоотделитель"
      },
      {
        "dir": 2,
        "pos": [
          15,
          4,
          84
        ],
        "text": "регионализация"
      },
      {
        "dir": 2,
        "pos": [
          16,
          2,
          95
        ],
        "text": "каландрование"
      },
      {
        "dir": 3,
        "pos": [
          9,
          11,
          96
        ],
        "text": "электрооборудование"
      },
      {
        "dir": 1,
        "pos": [
          27,
          24,
          99
        ],
        "text": "подтаскивание"
      },
      {
        "dir": 2,
        "pos": [
          15,
          23,
          85
        ],
        "text": "нежелательность"
      },
      {
        "dir": 1,
        "pos": [
          13,
          12,
          99
        ],
        "text": "высовывание"
      },
      {
        "dir": 2,
        "pos": [
          17,
          26,
          92
        ],
        "text": "заламывание"
      },
      {
        "dir": 2,
        "pos": [
          9,
          21,
          94
        ],
        "text": "дискредитирование"
      },
      {
        "dir": 2,
        "pos": [
          0,
          16,
          85
        ],
        "text": "аккомпанирование"
      },
      {
        "dir": 3,
        "pos": [
          23,
          12,
          96
        ],
        "text": "асфальтировщица"
      },
      {
        "dir": 2,
        "pos": [
          0,
          15,
          98
        ],
        "text": "перебегание"
      },
      {
        "dir": 3,
        "pos": [
          7,
          12,
          92
        ],
        "text": "закислённость"
      },
      {
        "dir": 1,
        "pos": [
          1,
          0,
          21
        ],
        "text": "трансформаторостроение"
      },
      {
        "dir": 1,
        "pos": [
          7,
          13,
          99
        ],
        "text": "вычитывание"
      },
      {
        "dir": 3,
        "pos": [
          9,
          0,
          95
        ],
        "text": "выбеливание"
      },
      {
        "dir": 1,
        "pos": [
          5,
          1,
          94
        ],
        "text": "разминирование"
      },
      {
        "dir": 1,
        "pos": [
          18,
          29,
          99
        ],
        "text": "налаживание"
      },
      {
        "dir": 2,
        "pos": [
          16,
          19,
          96
        ],
        "text": "авиамагистраль"
      },
      {
        "dir": 2,
        "pos": [
          13,
          24,
          96
        ],
        "text": "неопровержимость"
      },
      {
        "dir": 1,
        "pos": [
          5,
          20,
          99
        ],
        "text": "трудотерапия"
      },
      {
        "dir": 3,
        "pos": [
          23,
          13,
          99
        ],
        "text": "фехтовальщик"
      },
      {
        "dir": 3,
        "pos": [
          7,
          5,
          86
        ],
        "text": "неразгаданность"
      },
      {
        "dir": 1,
        "pos": [
          3,
          16,
          97
        ],
        "text": "самодеятельность"
      },
      {
        "dir": 3,
        "pos": [
          1,
          1,
          45
        ],
        "text": "пролетаризирование"
      },
      {
        "dir": 2,
        "pos": [
          0,
          10,
          89
        ],
        "text": "освободительница"
      },
      {
        "dir": 2,
        "pos": [
          0,
          0,
          5
        ],
        "text": "пролащивание"
      },
      {
        "dir": 1,
        "pos": [
          21,
          16,
          99
        ],
        "text": "формулировка"
      },
      {
        "dir": 1,
        "pos": [
          19,
          19,
          97
        ],
        "text": "развинчивание"
      },
      {
        "dir": 1,
        "pos": [
          25,
          2,
          99
        ],
        "text": "протагонистка"
      },
      {
        "dir": 1,
        "pos": [
          1,
          1,
          96
        ],
        "text": "поступательность"
      },
      {
        "dir": 1,
        "pos": [
          11,
          26,
          99
        ],
        "text": "бездуховность"
      },
      {
        "dir": 3,
        "pos": [
          5,
          6,
          99
        ],
        "text": "раздельнополость"
      },
      {
        "dir": 3,
        "pos": [
          7,
          17,
          96
        ],
        "text": "нецензурность"
      },
      {
        "dir": 1,
        "pos": [
          22,
          2,
          99
        ],
        "text": "выстругивание"
      },
      {
        "dir": 1,
        "pos": [
          3,
          13,
          99
        ],
        "text": "палеографист"
      },
      {
        "dir": 1,
        "pos": [
          21,
          24,
          99
        ],
        "text": "микроцефалия"
      },
      {
        "dir": 1,
        "pos": [
          27,
          8,
          99
        ],
        "text": "многовластие"
      },
      {
        "dir": 1,
        "pos": [
          14,
          0,
          15
        ],
        "text": "перебинтовывание"
      },
      {
        "dir": 1,
        "pos": [
          1,
          22,
          99
        ],
        "text": "автомашинист"
      },
      {
        "dir": 1,
        "pos": [
          1,
          29,
          99
        ],
        "text": "дермографизм"
      },
      {
        "dir": 1,
        "pos": [
          7,
          1,
          99
        ],
        "text": "успокаивание"
      },
      {
        "dir": 1,
        "pos": [
          7,
          26,
          99
        ],
        "text": "полосчатость"
      },
      {
        "dir": 1,
        "pos": [
          29,
          8,
          99
        ],
        "text": "резервирование"
      }
    ]
  }
}